skryptorium/__init__.py
skryptorium/cli.py
skryptorium/hello.py
skryptorium-0.0.1.dist-info/LICENSE
skryptorium-0.0.1.dist-info/METADATA
skryptorium-0.0.1.dist-info/WHEEL
skryptorium-0.0.1.dist-info/entry_points.txt
skryptorium-0.0.1.dist-info/top_level.txt
skryptorium-0.0.1.dist-info/RECORD
