Metadata-Version: 2.1
Name: skryptorium
Version: 0.0.1
Summary: Tools for working with single-cell DNA sequencing data
Author-email: Ajay Khanna <appliedstochastics@gmail.com>
License: MIT
Classifier: Programming Language :: Python :: 3
Requires-Python: >3.7
License-File: LICENSE
